{
    "name": "Adult Black Dragon",
    "source": "MM",
    "size": "huge",
    "type": "dragon",
    "tags": [],
    "alignment": "chaotic evil",
    "abilities": {
        "STR": {
            "name": "Strength",
            "score": 23,
            "modifier": 6
        },
        "DEX": {
            "name": "Dexterity",
            "score": 14,
            "modifier": 2
        },
        "CON": {
            "name": "Constitution",
            "score": 21,
            "modifier": 5
        },
        "INT": {
            "name": "Intelligence",
            "score": 14,
            "modifier": 2
        },
        "WIS": {
            "name": "Wisdom",
            "score": 13,
            "modifier": 1
        },
        "CHA": {
            "name": "Charisma",
            "score": 17,
            "modifier": 3
        }
    },
    "ac": {
        "value": 19,
        "info": "natural armor"
    },
    "hp": {
        "hit points": 195,
        "hit dice": "17d12 + 85"
    },
    "speeds": {
        "core": {
            "walk": "40 ft.",
            "fly": "80 ft.",
            "swim": "40 ft."
        },
        "forms": []
    },
    "savingThrows": {
        "dex": 7,
        "con": 10,
        "wis": 6,
        "cha": 8
    },
    "skillThrows": {
        "perception": 11,
        "stealth": 7
    },
    "damageVulnerabilities": [],
    "damageResistances": [],
    "damageImmunities": [
        {
            "condition": "",
            "items": [
                "acid"
            ]
        }
    ],
    "conditionImmunities": [],
    "senses": {
        "blindsight": "60 ft.",
        "darkvision": "120 ft.",
        "passive Perception": 21
    },
    "languages": "Common, Draconic",
    "challenge": {
        "rating": 14,
        "xp": "11,500 XP"
    },
    "traits": [
        {
            "name": "amphibious.",
            "description": "The dragon can breathe air and water.",
            "extra": []
        },
        {
            "name": "legendary resistance (3\/day).",
            "description": "If the dragon fails a saving throw, it can choose to succeed instead.",
            "extra": []
        }
    ],
    "actions": [
        {
            "name": "multiattack.",
            "description": "The dragon can use its Frightful Presence. It then makes three attacks: one with its bite and two with its claws.",
            "extra": []
        },
        {
            "name": "bite.",
            "description": "Melee Weapon Attack: +11 to hit, reach 10 ft., one target. Hit: 17 (2d10 + 6) piercing damage plus 4 (1d8) acid damage.",
            "extra": [],
            "tohit": "1d20+11",
            "damages": {
                "or": [
                    {
                        "type": "piercing",
                        "average": 17,
                        "dice": "2d10 + 6"
                    }
                ],
                "plus": {
                    "type": "acid",
                    "average": 4,
                    "dice": "1d8"
                }
            }
        },
        {
            "name": "claw.",
            "description": "Melee Weapon Attack: +11 to hit, reach 5 ft., one target. Hit: 13 (2d6 + 6) slashing damage.",
            "extra": [],
            "tohit": "1d20+11",
            "damages": {
                "or": [
                    {
                        "type": "slashing",
                        "average": 13,
                        "dice": "2d6 + 6"
                    }
                ]
            }
        },
        {
            "name": "tail.",
            "description": "Melee Weapon Attack: +11 to hit, reach 15 ft., one target. Hit: 15 (2d8 + 6) bludgeoning damage.",
            "extra": [],
            "tohit": "1d20+11",
            "damages": {
                "or": [
                    {
                        "type": "bludgeoning",
                        "average": 15,
                        "dice": "2d8 + 6"
                    }
                ]
            }
        },
        {
            "name": "frightful presence.",
            "description": "Each creature of the dragon's choice that is within 120 feet of the dragon and aware of it must succeed on a DC 16 Wisdom saving throw or become frightened for 1 minute. A creature can repeat the saving throw at the end of each of its turns, ending the effect on itself on a success. If a creature's saving throw is successful or the effect ends for it, the creature is immune to the dragon's Frightful Presence for the next 24 hours.",
            "extra": []
        },
        {
            "name": "acid breath (recharge 5-6).",
            "description": "The dragon exhales acid in a 60-foot line that is 5 feet wide. Each creature in that line must make a DC 18 Dexterity saving throw, taking 54 (12d8) acid damage on a failed save, or half as much damage on a successful one.",
            "extra": []
        }
    ],
    "legendary": {
        "intro": "The dragon can take 3 legendary actions, choosing from the options below. Only one legendary action option can be used at a time and only at the end of another creature's turn. The dragon regains spent legendary actions at the start of its turn.",
        "actions": [
            {
                "name": "detect.",
                "description": "The dragon makes a Wisdom (Perception) check."
            },
            {
                "name": "tail attack.",
                "description": "The dragon makes a tail attack."
            },
            {
                "name": "wing attack (costs 2 actions).",
                "description": "The dragon beats its wings. Each creature within 10 feet of the dragon must succeed on a DC 19 Dexterity saving throw or take 13 (2d6 + 6) bludgeoning damage and be knocked prone. The dragon can then fly up to half its flying speed."
            }
        ]
    }
}