{
    "id": "greataxe",
    "name": "Greataxe",
    "description": [
        "Proficiency with a greataxe allows you to add your proficiency bonus to the attack roll for any attack you make with it."
    ],
    "weight": 7,
    "category": "weapons",
    "subcategory": "martial melee weapons",
    "cost": {
        "normal": 3000,
        "cheap": 2200,
        "expensive": 4500
    },
    "stores": {
        "blacksmith": [
            "rural",
            "urban",
            "premium"
        ]
    },
    "themes": [],
    "url": "https:\/\/www.dndbeyond.com\/equipment\/greataxe"
}